aliyunsdkidrsservice/__init__.py
aliyunsdkidrsservice/endpoint.py
aliyunsdkidrsservice/request/__init__.py
aliyunsdkidrsservice/request/v20200630/CheckServiceLinkedRoleRequest.py
aliyunsdkidrsservice/request/v20200630/CreateAppRequest.py
aliyunsdkidrsservice/request/v20200630/CreateDepartmentRequest.py
aliyunsdkidrsservice/request/v20200630/CreateLiveDetectionRequest.py
aliyunsdkidrsservice/request/v20200630/CreateLiveRequest.py
aliyunsdkidrsservice/request/v20200630/CreateRuleRequest.py
aliyunsdkidrsservice/request/v20200630/CreateStatisticsRecordRequest.py
aliyunsdkidrsservice/request/v20200630/CreateStatisticsTaskRequest.py
aliyunsdkidrsservice/request/v20200630/CreateTaskGroupRequest.py
aliyunsdkidrsservice/request/v20200630/CreateUserDepartmentsRequest.py
aliyunsdkidrsservice/request/v20200630/DeleteAppRequest.py
aliyunsdkidrsservice/request/v20200630/DeleteDepartmentRequest.py
aliyunsdkidrsservice/request/v20200630/DeleteRuleRequest.py
aliyunsdkidrsservice/request/v20200630/DeleteUserDepartmentsRequest.py
aliyunsdkidrsservice/request/v20200630/DeleteUserRequest.py
aliyunsdkidrsservice/request/v20200630/ExitLiveRequest.py
aliyunsdkidrsservice/request/v20200630/GetAppRequest.py
aliyunsdkidrsservice/request/v20200630/GetDepartmentRequest.py
aliyunsdkidrsservice/request/v20200630/GetDetectEvaluationRequest.py
aliyunsdkidrsservice/request/v20200630/GetDetectionRequest.py
aliyunsdkidrsservice/request/v20200630/GetModelSignedUrlRequest.py
aliyunsdkidrsservice/request/v20200630/GetPreSignedUrlRequest.py
aliyunsdkidrsservice/request/v20200630/GetRuleRequest.py
aliyunsdkidrsservice/request/v20200630/GetServiceConfigurationRequest.py
aliyunsdkidrsservice/request/v20200630/GetSignedUrlRequest.py
aliyunsdkidrsservice/request/v20200630/GetSlrConfigurationRequest.py
aliyunsdkidrsservice/request/v20200630/GetStatisticsRequest.py
aliyunsdkidrsservice/request/v20200630/GetTaskGroupRequest.py
aliyunsdkidrsservice/request/v20200630/GetTaskRequest.py
aliyun_python_sdk_idrsservice-0.1.1.dist-info/LICENSE
aliyun_python_sdk_idrsservice-0.1.1.dist-info/METADATA
aliyun_python_sdk_idrsservice-0.1.1.dist-info/WHEEL
aliyun_python_sdk_idrsservice-0.1.1.dist-info/top_level.txt
aliyun_python_sdk_idrsservice-0.1.1.dist-info/RECORD
